visual_debugger/__init__.py
visual_debugger/annotation_processor.py
visual_debugger/annotations.py
visual_debugger/composition.py
visual_debugger/image_processor.py
visual_debugger/info_panel.py
visual_debugger/old_annotations.py
visual_debugger/visual_debugger.py
visual_debugger-0.4.1.dist-info/METADATA
visual_debugger-0.4.1.dist-info/WHEEL
visual_debugger-0.4.1.dist-info/top_level.txt
visual_debugger-0.4.1.dist-info/RECORD
